scout_service_api/__init__.py
scout_service_api/_impl.py
scout_service_api/py.typed
scout_service_api/scout/__init__.py
scout_service_api/scout_run_api/__init__.py
scout_service_api-0.1.0.dist-info/METADATA
scout_service_api-0.1.0.dist-info/WHEEL
scout_service_api-0.1.0.dist-info/top_level.txt
scout_service_api-0.1.0.dist-info/RECORD
