Metadata-Version: 2.1
Name: scout-service-api
Version: 0.1.0
Requires-Python: >=3.8
Requires-Dist: requests
Requires-Dist: conjure-python-client <3,>=2.8.0
